thunderstormAPI/__init__.py
thunderstormAPI/thunderstorm.py
thunderstormAPI/thunderstorm_cli.py
venv/__init__.py
venv/lib/__init__.py
thunderstormAPI-0.1.1.dist-info/LICENSE
thunderstormAPI-0.1.1.dist-info/METADATA
thunderstormAPI-0.1.1.dist-info/WHEEL
thunderstormAPI-0.1.1.dist-info/entry_points.txt
thunderstormAPI-0.1.1.dist-info/top_level.txt
thunderstormAPI-0.1.1.dist-info/RECORD
