Metadata-Version: 2.1
Name: thunderstormAPI
Version: 0.1.1
Summary: THOR Thunderstorm Service API Client
Home-page: https://github.com/NextronSystems/thunderstormAPI
Author: Florian Roth
Author-email: florian.roth@nextron-systems.com
License: UNKNOWN
Platform: UNKNOWN
Classifier: Programming Language :: Python :: 3
Classifier: License :: OSI Approved :: Apache Software License
Classifier: Operating System :: OS Independent
Requires-Python: ~=3.5
Requires-Dist: packaging
Requires-Dist: requests
Requires-Dist: configparser
